LICENSE
MANIFEST.in
README.md
pyproject.toml
setup.cfg
setup.py
esbonio/__main__.py
esbonio/cli.py
esbonio/py.typed
esbonio/lsp/__init__.py
esbonio/lsp/directives.py
esbonio/lsp/log.py
esbonio/lsp/roles.py
esbonio/lsp/spelling.py
esbonio/lsp/symbols.py
esbonio/lsp/testing.py
esbonio/lsp/rst/__init__.py
esbonio/lsp/rst/__main__.py
esbonio/lsp/rst/_record.py
esbonio/lsp/rst/directives.json
esbonio/lsp/rst/directives.py
esbonio/lsp/rst/io.py
esbonio/lsp/rst/roles.json
esbonio/lsp/rst/roles.py
esbonio/lsp/sphinx/__init__.py
esbonio/lsp/sphinx/__main__.py
esbonio/lsp/sphinx/_record.py
esbonio/lsp/sphinx/cli.py
esbonio/lsp/sphinx/codeblocks.py
esbonio/lsp/sphinx/config.py
esbonio/lsp/sphinx/directives.json
esbonio/lsp/sphinx/directives.py
esbonio/lsp/sphinx/domains.py
esbonio/lsp/sphinx/images.py
esbonio/lsp/sphinx/includes.py
esbonio/lsp/sphinx/line_number_transform.py
esbonio/lsp/sphinx/preview.py
esbonio/lsp/sphinx/roles.json
esbonio/lsp/sphinx/roles.py
esbonio/lsp/util/__init__.py
esbonio/lsp/util/filepaths.py
esbonio/lsp/util/inspect.py
esbonio/lsp/util/patterns.py
esbonio_lextudio.egg-info/PKG-INFO
esbonio_lextudio.egg-info/SOURCES.txt
esbonio_lextudio.egg-info/dependency_links.txt
esbonio_lextudio.egg-info/entry_points.txt
esbonio_lextudio.egg-info/requires.txt
esbonio_lextudio.egg-info/top_level.txt