Metadata-Version: 2.1
Name: esbonio-lextudio
Version: 0.14.1
Summary: A Language Server for Sphinx projects.
Home-page: https://swyddfa.github.io/esbonio/
Author: Alex Carney
Author-email: alcarneyme@gmail.com
License: MIT
Project-URL: Bug Tracker, https://github.com/swyddfa/esbonio/issues
Project-URL: Documentation, https://swyddfa.github.io/esbonio/
Project-URL: Source Code, https://github.com/swyddfa/esbonio
Platform: any
Classifier: Development Status :: 3 - Alpha
Classifier: License :: OSI Approved :: MIT License
Classifier: Programming Language :: Python
Classifier: Programming Language :: Python :: 3
Classifier: Programming Language :: Python :: 3 :: Only
Classifier: Programming Language :: Python :: 3.6
Classifier: Programming Language :: Python :: 3.7
Classifier: Programming Language :: Python :: 3.8
Classifier: Programming Language :: Python :: 3.9
Classifier: Programming Language :: Python :: 3.10
Classifier: Topic :: Documentation
Classifier: Topic :: Documentation :: Sphinx
Provides-Extra: debug
Provides-Extra: dev
License-File: LICENSE
